scrapex/__init__.py
scrapex/_name.py
scrapex/agent.py
scrapex/cache.py
scrapex/common.py
scrapex/core.py
scrapex/db.py
scrapex/doc.py
scrapex/excellib.py
scrapex/http.py
scrapex/node.py
scrapex/proxy.py
scrapex/worker.py
scrapex-0.2.2.dist-info/LICENSE
scrapex-0.2.2.dist-info/METADATA
scrapex-0.2.2.dist-info/WHEEL
scrapex-0.2.2.dist-info/top_level.txt
scrapex-0.2.2.dist-info/RECORD
