Metadata-Version: 2.1
Name: scrapex
Version: 0.2.2
Summary: A simple web scraping framework in Python
Home-page: https://github.com/cungnv/scrapex
Author: Cung Nguyen
Author-email: cungjava2000@gmail.com
License: MIT
Download-URL: https://github.com/cungnv/scrapex/archive/master.zip
Platform: UNKNOWN
Classifier: Intended Audience :: Developers
Classifier: Natural Language :: English
Classifier: Programming Language :: Python
Classifier: Programming Language :: Python :: 2
Classifier: Programming Language :: Python :: 2.7
Classifier: Programming Language :: Python :: 3
Classifier: Programming Language :: Python :: 3.5
Classifier: Programming Language :: Python :: 3.6
Classifier: Programming Language :: Python :: 3.7
Classifier: Programming Language :: Python :: 3.8
Requires-Dist: lxml
Requires-Dist: requests
Requires-Dist: openpyxl
Requires-Dist: pyOpenSSL
Requires-Dist: future
